mzflaskfive/MzChess.py
mzflaskfive/MzView.py
mzflaskfive/__init__.py
mzflaskfive/static/__init__.py
mzflaskfive/static/black.png
mzflaskfive/static/chessboard.jpg
mzflaskfive/static/white.png
mzflaskfive/templates/__init__.py
mzflaskfive/templates/index.html
mzflaskfive-0.1.2.dist-info/LICENSE
mzflaskfive-0.1.2.dist-info/METADATA
mzflaskfive-0.1.2.dist-info/WHEEL
mzflaskfive-0.1.2.dist-info/top_level.txt
mzflaskfive-0.1.2.dist-info/RECORD
