Metadata-Version: 2.1
Name: mzflaskfive
Version: 0.1.2
Summary: A flask five
Home-page: https://gitee.com/egg34/mzflaskfive
Author: Mz1
Author-email: mzi_mzi@163.com
License: UNKNOWN
Platform: UNKNOWN
Classifier: Programming Language :: Python :: 3
Classifier: License :: OSI Approved :: MIT License
Classifier: Operating System :: OS Independent
Requires-Python: >=3.5
License-File: LICENSE
Requires-Dist: Flask
